sedql/__init__.py
sedql/cli.py
sedql/client.py
sedql/exceptions.py
sedql-1.0.10.dist-info/METADATA
sedql-1.0.10.dist-info/WHEEL
sedql-1.0.10.dist-info/entry_points.txt
sedql-1.0.10.dist-info/top_level.txt
sedql-1.0.10.dist-info/RECORD
