Metadata-Version: 2.4
Name: sedql
Version: 1.0.10
Summary: Python SDK for SED (Semantic Entities Designs) - Full TypeScript CLI Integration
Home-page: https://github.com/holy182/sed-cli
Author: SED Team
Maintainer: SED Team
License-Expression: AGPL-3.0
Project-URL: Homepage, https://github.com/holy182/sed-cli
Project-URL: Documentation, https://github.com/holy182/sed-cli#readme
Project-URL: Repository, https://github.com/holy182/sed-cli
Project-URL: Bug Tracker, https://github.com/holy182/sed-cli/issues
Keywords: semantic,database,ai,dsl,data-modeling,automation,sed,cli
Classifier: Development Status :: 4 - Beta
Classifier: Intended Audience :: Developers
Classifier: Intended Audience :: Science/Research
Classifier: Operating System :: OS Independent
Classifier: Programming Language :: Python :: 3
Classifier: Programming Language :: Python :: 3.8
Classifier: Programming Language :: Python :: 3.9
Classifier: Programming Language :: Python :: 3.10
Classifier: Programming Language :: Python :: 3.11
Classifier: Programming Language :: Python :: 3.12
Classifier: Topic :: Database
Classifier: Topic :: Scientific/Engineering :: Information Analysis
Classifier: Topic :: Software Development :: Libraries :: Python Modules
Classifier: Topic :: Scientific/Engineering :: Artificial Intelligence
Requires-Python: >=3.8
Provides-Extra: dev
Requires-Dist: pytest>=6.0; extra == "dev"
Requires-Dist: black>=21.0; extra == "dev"
Requires-Dist: flake8>=3.8; extra == "dev"
Dynamic: home-page
Dynamic: requires-python
